habutax/__init__.py
habutax/__main__.py
habutax/enum.py
habutax/fields.py
habutax/form.py
habutax/inputs.py
habutax/pdf_fields.py
habutax/pdf_filler.py
habutax/solver.py
habutax/values.py
habutax/forms/__init__.py
habutax/forms/ty2021/__init__.py
habutax/forms/ty2021/f1040.pdf
habutax/forms/ty2021/f1040.py
habutax/forms/ty2021/f1040_figure_tax.py
habutax/forms/ty2021/f1040_qualdiv_capgain_tax_wkst.py
habutax/forms/ty2021/f1040_recovery_rebate_credit_wkst.py
habutax/forms/ty2021/f1040_s1.py
habutax/forms/ty2021/f1040_s2_need6251.py
habutax/forms/ty2021/f1040_s3.py
habutax/forms/ty2021/f1040_s8812.py
habutax/forms/ty2021/f1040_sa.py
habutax/forms/ty2021/f1040_sb.py
habutax/forms/ty2021/f1040s1.pdf
habutax/forms/ty2021/f1040s3.pdf
habutax/forms/ty2021/f1040s8.pdf
habutax/forms/ty2021/f1040sa.pdf
habutax/forms/ty2021/f1040sb.pdf
habutax/forms/ty2021/f1098.py
habutax/forms/ty2021/f1099_div.py
habutax/forms/ty2021/f1099_g.py
habutax/forms/ty2021/f1099_int.py
habutax/forms/ty2021/f1099_r.py
habutax/forms/ty2021/f8606.pdf
habutax/forms/ty2021/f8606.py
habutax/forms/ty2021/f8889.pdf
habutax/forms/ty2021/f8889.py
habutax/forms/ty2021/f8959.pdf
habutax/forms/ty2021/f8959.py
habutax/forms/ty2021/f8995.pdf
habutax/forms/ty2021/f8995.py
habutax/forms/ty2021/fnc_d-400.pdf
habutax/forms/ty2021/fnc_d-400_sa.pdf
habutax/forms/ty2021/fnc_d-400_ss.pdf
habutax/forms/ty2021/fnc_d_400.py
habutax/forms/ty2021/fnc_d_400_child_deduction_wkst.py
habutax/forms/ty2021/fnc_d_400_consumer_use_tax_wkst.py
habutax/forms/ty2021/fnc_d_400_sa.py
habutax/forms/ty2021/fnc_d_400_ss.py
habutax/forms/ty2021/fw_2.py
habutax/forms/ty2022/__init__.py
habutax/forms/ty2022/f1040.pdf
habutax/forms/ty2022/f1040.py
habutax/forms/ty2022/f1040_figure_tax.py
habutax/forms/ty2022/f1040_qualdiv_capgain_tax_wkst.py
habutax/forms/ty2022/f1040_s1.py
habutax/forms/ty2022/f1040_s2_need6251.py
habutax/forms/ty2022/f1040_s3.py
habutax/forms/ty2022/f1040_s8812.py
habutax/forms/ty2022/f1040_sa.py
habutax-0.2.1.dist-info/LICENSE
habutax-0.2.1.dist-info/METADATA
habutax-0.2.1.dist-info/WHEEL
habutax-0.2.1.dist-info/entry_points.txt
habutax-0.2.1.dist-info/top_level.txt
habutax-0.2.1.dist-info/RECORD
