Metadata-Version: 2.1
Name: habutax
Version: 0.2.1
Summary: Open-source tax solver for US personal income tax returns
Home-page: https://github.com/habutax/habutax
Author: Aaron Lindsay
Author-email: habutax@gmail.com
Project-URL: Bug Tracker, https://github.com/habutax/habutax/issues
Classifier: Development Status :: 3 - Alpha
Classifier: Programming Language :: Python :: 3
Classifier: Environment :: Console
Classifier: Operating System :: OS Independent
Classifier: License :: OSI Approved :: GNU General Public License v2 (GPLv2)
Requires-Python: >=3.8
License-File: LICENSE
